contact/__init__.py
contact/admin.py
contact/apps.py
contact/static/css/contact/bethany_ds.css
contact/static/css/contact/medicio_ds.css
contact/static/css/contact/medilab_ds.css
contact/static/css/contact/mentor_ds.css
contact/templates/contact/_common.html
contact/templates/contact/bethany_ds.html
contact/templates/contact/medicio_ds.html
contact/templates/contact/medilab_ds.html
contact/templates/contact/mentor_ds.html
contact/templatetags/__init__.py
contact/templatetags/contact_tags.py
mentor_ds/__init__.py
mentor_ds/admin.py
mentor_ds/apps.py
mentor_ds/models.py
mentor_ds/urls.py
mentor_ds/views.py
mentor_ds/migrations/__init__.py
django_contact_ds-0.2.1.dist-info/LICENSE
django_contact_ds-0.2.1.dist-info/METADATA
django_contact_ds-0.2.1.dist-info/WHEEL
django_contact_ds-0.2.1.dist-info/top_level.txt
django_contact_ds-0.2.1.dist-info/RECORD
